[{"word": "Installation Steps", "bounding_box": [127, 132, 1260, 306]}, {"word": "Activate and Test", "bounding_box": [137, 367, 566, 421]}, {"word": "connecting the Intercom to Wi-Fi without WPS", "bounding_box": [1463, 565, 2320, 627]}, {"word": "All systems must be activated once installation is", "bounding_box": [140, 572, 1040, 624]}, {"word": "If", "bounding_box": [1434, 575, 1466, 613]}, {"word": "complete and while the installer is on-site.", "bounding_box": [137, 632, 906, 682]}, {"word": "While activating the Intercom with ButterflyMX", "bounding_box": [1433, 741, 2258, 802]}, {"word": "Activation will verify all systems are operational,", "bounding_box": [137, 747, 986, 801]}, {"word": "Support, ask to configure Wi-Fi.", "bounding_box": [1430, 799, 1997, 863]}, {"word": "document installed hardware, and activate the", "bounding_box": [137, 805, 960, 855]}, {"word": "ButterflyMX system. Activation is done by calling", "bounding_box": [136, 859, 1002, 920]}, {"word": "Be prepared to provide the desired networks", "bounding_box": [1433, 920, 2229, 980]}, {"word": "ButterflyMX Support while the installer is on-site at", "bounding_box": [137, 923, 1042, 978]}, {"word": "(800) 398-4416, ext 2.", "bounding_box": [135, 980, 535, 1030]}, {"word": "SSID and password.", "bounding_box": [1432, 980, 1789, 1033]}, {"word": "Be prepared to provide wiring specifications,", "bounding_box": [137, 1095, 929, 1152]}, {"word": "Once ButterflyMX Support has connected the", "bounding_box": [1434, 1098, 2244, 1153]}, {"word": "building address, and Intercom serial number.", "bounding_box": [136, 1153, 965, 1208]}, {"word": "Intercom to Wi-Fi, disconnect Ethernet cable from", "bounding_box": [1432, 1154, 2318, 1206]}, {"word": "the Intercom and network equipment:", "bounding_box": [1432, 1215, 2100, 1267]}, {"word": "ButterflyMX support will work with the installer to", "bounding_box": [135, 1267, 1010, 1329]}, {"word": "test video calls and PIN codes for confirmation of", "bounding_box": [135, 1329, 1012, 1379]}, {"word": "In its current location, verify Intercom is", "bounding_box": [1432, 1329, 2133, 1381]}, {"word": "installation steps and verification Intercom", "bounding_box": [135, 1389, 885, 1444]}, {"word": "connected to Wi-Fi.", "bounding_box": [1433, 1391, 1787, 1433]}, {"word": "functionality.", "bounding_box": [134, 1447, 367, 1499]}, {"word": "Once in its final installation location, verify that", "bounding_box": [1434, 1504, 2259, 1556]}, {"word": "Please schedule installations with this requirement", "bounding_box": [137, 1561, 1033, 1617]}, {"word": "there is still an established Wi-Fi connection:", "bounding_box": [1433, 1567, 2222, 1609]}, {"word": "in mind.", "bounding_box": [136, 1626, 278, 1665]}, {"word": "Activation is required:", "bounding_box": [973, 2196, 2246, 2366]}, {"word": "STOP", "bounding_box": [222, 2215, 638, 2360]}, {"word": "ButterflyMX will notify the client that installation is complete and will begin onboarding:", "bounding_box": [135, 2844, 1697, 2896]}, {"word": "AIl documentation can be found on https:|/butterflymx com/resources/installers/documentation.", "bounding_box": [134, 2897, 1858, 2957]}, {"word": "ButterflyMX", "bounding_box": [180, 3142, 476, 3207]}, {"word": "19", "bounding_box": [2396, 3146, 2463, 3200]}, {"word": "Installation Guide", "bounding_box": [1456, 3155, 1807, 3199]}, {"word": "Surface Mount Intercom", "bounding_box": [1822, 3155, 2315, 3199]}]