[{"word": "Installation Steps", "bounding_box": [120, 128, 1263, 313]}, {"word": "Connect Relay(s)", "bounding_box": [129, 364, 562, 431]}, {"word": "Credentia", "bounding_box": [2736, 425, 2786, 439]}, {"word": "The Intercom requires diodes (for DC locks) or varistors (for AC Iocks). This ButterflyMX Intercom does not require an isolation", "bounding_box": [132, 471, 2098, 516]}, {"word": "Tnstaltling an TsotationTelay, the circuit thatpowers the lock needs to be isolated from the circuit that powers", "bounding_box": [400, 515, 2091, 571]}, {"word": "Telay: However; Tf", "bounding_box": [132, 525, 409, 566]}, {"word": "[the Tetay with two separate power supplies:", "bounding_box": [127, 569, 812, 620]}, {"word": "Contirm Wieqand format", "bounding_box": [2859, 795, 2981, 809]}, {"word": "Ifahn Ats is present:", "bounding_box": [130, 807, 630, 873]}, {"word": "Ifadifferent", "bounding_box": [3149, 914, 3209, 935]}, {"word": "Wiedand 28-6", "bounding_box": [2859, 915, 2929, 929]}, {"word": "Or, connect relay to existing REX input:", "bounding_box": [1430, 940, 2139, 997]}, {"word": "lonnect relay to designated input:", "bounding_box": [310, 944, 912, 997]}, {"word": "2", "bounding_box": [1271, 953, 1361, 1058]}, {"word": "1", "bounding_box": [142, 959, 208, 1056]}, {"word": "act SolutionsArchitecture@BL", "bounding_box": [2967, 995, 3104, 1009]}, {"word": "If a designated input is not available, connect {he", "bounding_box": [1430, 1000, 2302, 1056]}, {"word": "relay from the Intercom will need to", "bounding_box": [314, 1004, 948, 1055]}, {"word": "pnnect to the third-party ACS designated", "bounding_box": [302, 1063, 1039, 1115]}, {"word": "Tntercom relay into the dxisting REXinput on the", "bounding_box": [1430, 1063, 2283, 1115]}, {"word": "1d facility", "bounding_box": [2963, 1066, 3005, 1080]}, {"word": "Ired fobor tag", "bounding_box": [3074, 1066, 3136, 1080]}, {"word": "programmed to release", "bounding_box": [1886, 1117, 2307, 1179]}, {"word": "input Consult +ith yetr thire party AeS", "bounding_box": [278, 1119, 992, 1171]}, {"word": "ACS,as it mnay alreae- Ue", "bounding_box": [1430, 1119, 1884, 1171]}, {"word": "sppport to configure -the input -to unock", "bounding_box": [282, 1177, 992, 1231]}, {"word": "the deer", "bounding_box": [1427, 1184, 1596, 1226]}, {"word": "Call Butt", "bounding_box": [2855, 1206, 2901, 1220]}, {"word": "format", "bounding_box": [3110, 1206, 3144, 1220]}, {"word": "theloch", "bounding_box": [279, 1240, 413, 1285]}, {"word": "Is installed and provisioned scana", "bounding_box": [2987, 1325, 3148, 1339]}, {"word": "ndsha", "bounding_box": [3166, 1325, 3200, 1339]}, {"word": "expected credential", "bounding_box": [2851, 1401, 2949, 1415]}, {"word": "matdetailswIth Support Thevwillcontirm thatthe format", "bounding_box": [2959, 1401, 3228, 1415]}, {"word": "ButterflyMXOS matches the expected formatofthe fob", "bounding_box": [2931, 1475, 3188, 1496]}, {"word": "If an AcSis not present:", "bounding_box": [130, 1477, 723, 1539]}, {"word": "ingin the", "bounding_box": [2887, 1481, 2933, 1495]}, {"word": "Ensure proper installation:", "bounding_box": [1432, 1608, 1920, 1662]}, {"word": "CpnnectTelay t0 Tocks power supply:", "bounding_box": [282, 1613, 968, 1665]}, {"word": "rflyMXoS", "bounding_box": [3007, 1620, 3053, 1638]}, {"word": "2", "bounding_box": [1272, 1623, 1352, 1723]}, {"word": "Enroll Credentials in th", "bounding_box": [2863, 1624, 2973, 1638]}, {"word": "The Intereom relay #ilneed- to interfaee", "bounding_box": [282, 1669, 1000, 1721]}, {"word": "Ensure the diode/varistor is installed properly , as", "bounding_box": [1430, 1669, 2295, 1721]}, {"word": "~tose as possibte to etectric tocking hardware,", "bounding_box": [1430, 1728, 2251, 1785]}, {"word": "with the tocks power supply:", "bounding_box": [282, 1729, 788, 1781]}, {"word": "Credentialscar", "bounding_box": [2859, 1744, 2933, 1758]}, {"word": "added byscanning the fobon the", "bounding_box": [2951, 1744, 3108, 1762]}, {"word": "prevent damaging _the Intercom", "bounding_box": [1430, 1788, 1996, 1836]}, {"word": "uplcading in bulk", "bounding_box": [3038, 1819, 3125, 1840]}, {"word": "bulk contact", "bounding_box": [3238, 1819, 3304, 1833]}, {"word": "Wnlcad cedenti", "bounding_box": [3139, 1824, 3219, 1832]}, {"word": "ATTENT", "bounding_box": [2831, 2369, 2873, 2383]}, {"word": "Ison-site,", "bounding_box": [2730, 2611, 2779, 2631]}, {"word": "heinstalle", "bounding_box": [2677, 2617, 2729, 2625]}, {"word": "Svstemsare orerational documee", "bounding_box": [2784, 2744, 2937, 2758]}, {"word": "Installed hardivare and activate the svstem;", "bounding_box": [2947, 2744, 3148, 2758]}, {"word": "ButtertlvMX", "bounding_box": [2728, 3138, 2786, 3152]}, {"word": "[ButterflyMX", "bounding_box": [179, 3143, 474, 3199]}, {"word": "tand Inctallation Guide Wiegand-tn-OsnPConverte", "bounding_box": [3489, 3146, 3726, 3160]}, {"word": "16", "bounding_box": [2398, 3147, 2462, 3195]}, {"word": "Comratikilt", "bounding_box": [3394, 3151, 3454, 3159]}, {"word": "Installation Guide", "bounding_box": [1454, 3151, 1808, 3199]}, {"word": "Surface Mount Intercom", "bounding_box": [1820, 3151, 2314, 3199]}]