[{"word": "Compliance", "bounding_box": [195, 154, 791, 287]}, {"word": "Federal Communications Commission", "bounding_box": [200, 376, 1122, 441]}, {"word": "Interference Statement", "bounding_box": [199, 447, 775, 502]}, {"word": "This equipment has been tested and found to comply with the limits for a", "bounding_box": [201, 588, 1484, 641]}, {"word": "Class B digital device, pursuant to part 15 of the FCC Rules. These limits", "bounding_box": [201, 646, 1472, 699]}, {"word": "are designed to provide reasonable protection against harmful interference", "bounding_box": [201, 702, 1521, 758]}, {"word": "in a residential installation. This equipment generates, uses, and can", "bounding_box": [199, 762, 1400, 816]}, {"word": "radiate radio frequency energy and, if not installed and used in accordance", "bounding_box": [196, 821, 1521, 877]}, {"word": "with the instructions, may cause harmful interference to radio", "bounding_box": [201, 879, 1285, 930]}, {"word": "communications However; there is no guarantee that interference will not", "bounding_box": [201, 937, 1503, 991]}, {"word": "particular installation:", "bounding_box": [378, 992, 759, 1048]}, {"word": "occur in a", "bounding_box": [202, 1001, 376, 1040]}, {"word": "If this equipment does cause harmful interference to radio or television", "bounding_box": [199, 1111, 1446, 1166]}, {"word": "reception, which can be determined by turning the equipment off and on,", "bounding_box": [195, 1166, 1491, 1227]}, {"word": "the user is encouraged to try to correct the interference by one or more of", "bounding_box": [196, 1230, 1511, 1283]}, {"word": "following measures:", "bounding_box": [262, 1282, 626, 1343]}, {"word": "the", "bounding_box": [197, 1291, 265, 1331]}, {"word": "Reorient or relocate the receiving antenna.", "bounding_box": [256, 1400, 1004, 1456]}, {"word": "Increase the separation between the equipment and receiver:", "bounding_box": [255, 1461, 1339, 1518]}, {"word": "Connect the equipment into an outlet on a circuit different from that to", "bounding_box": [254, 1521, 1501, 1574]}, {"word": "which the receiver is connected.", "bounding_box": [256, 1581, 830, 1629]}, {"word": "experienced radio/TV technician for help.", "bounding_box": [682, 1632, 1415, 1695]}, {"word": "Consult the dealer or an", "bounding_box": [255, 1639, 685, 1682]}, {"word": "This device complies with Part 15 of the FCC Rules. Operation is subject", "bounding_box": [199, 1933, 1486, 1985]}, {"word": "to the following two conditions: (1) this device may not cause harmful", "bounding_box": [198, 1986, 1436, 2046]}, {"word": "interference, and (2) this device must accept any interference received,", "bounding_box": [196, 2048, 1472, 2101]}, {"word": "including interference that may cause undesired operation: Changes or", "bounding_box": [194, 2102, 1469, 2165]}, {"word": "modifications not expressly approved by the party responsible for", "bounding_box": [201, 2167, 1375, 2222]}, {"word": "compliance could void the user's authority to operate the equipment.", "bounding_box": [199, 2223, 1427, 2279]}, {"word": "ButterflyMX", "bounding_box": [231, 2451, 529, 2524]}]